{"id":119385,"url":"http://en.wikipedia.org/wiki/Kamoki_Tehsil","text":"=\"preserve\">Kamoke is a Tehsil of Gujranwala District. It is on the Grand Trunk Road now national highway. Its headquarters is at K\u0101moke, which is about 22\u00A0km from Gujranwala, the district capital. It is famous for its market of Basmati rice. It contains twenty-four Union Councils. Kamoke is a busy town on the GT road. Most people here are Rajputs and Jats and arian and depend on agriculture. Kamoke is famous for its burfy (a local sweet) and rice.\nKamoke is the city with the most mosques in Pakistan. There are two degree colleges, one for men and other for women. The city is divided into three reigons: Line par, sarak par and main bazar. There are four police stations (P.S.): P.S. Sadar Kamoki, P.S. City Kamoke, P.S. Eminabad and P.S. Wahndo.","categories":[],"infobox_types":[],"annotations":[{"uri":"Gujranwala_District","surface_form":"Gujranwala District","offset":34},{"uri":"Grand_Trunk_Road","surface_form":"Grand Trunk Road","offset":68}]}