{"id":153250,"url":"http://en.wikipedia.org/wiki/Courcelles-sur-Vesle","text":"Courcelles-sur-Vesle is a commune. It is found in the region Picardie in the Aisne department in the north of France. Its population is 295 (1999 census). Its density is 32 inhabitants/km\u00B2.\nHistory.\nIt's in this village that Napol\u00E9on met Marie-Louise, in front of the church, on March 27 1810. She became Empress of the French at just 19 years of age. At the time Napol\u00E9on was 41.\nAdministration.\nThe Mayor since 2001 has been Luc tordeux. He was re-elected in 2008. The next elections are in 2014.\nMonuments.\nThe remains of the choir of the old church have had Listed Building status since 1927.\nThe Chapel called \"Le Calvaire\", has been a Listed Building since 1929.\nThe Courcelles sur Vesle castle was built in 1694. It was ordered by the Baron Jacques de la Grange.\nIn 1988, it became a Hotel and a restaurant.","categories":[],"infobox_types":[],"annotations":[{"uri":"Communes_of_France","surface_form":"commune","offset":26},{"uri":"Regions_of_France","surface_form":"region","offset":54},{"uri":"Picardie","surface_form":"Picardie","offset":61},{"uri":"Aisne","surface_form":"Aisne","offset":77},{"uri":"Departments_of_France","surface_form":"department","offset":83},{"uri":"France","surface_form":"France","offset":110},{"uri":"1999","surface_form":"1999","offset":141},{"uri":"Napol%C3%A9on","surface_form":"Napol\u00E9on","offset":225},{"uri":"Church","surface_form":"church","offset":268},{"uri":"1927","surface_form":"1927","offset":591},{"uri":"1929","surface_form":"1929","offset":663},{"uri":"Castle","surface_form":"castle","offset":694},{"uri":"1694","surface_form":"1694","offset":714},{"uri":"Baron","surface_form":"Baron","offset":742},{"uri":"Hotel","surface_form":"Hotel","offset":791},{"uri":"Restaurant","surface_form":"restaurant","offset":803}]}