{"id":154648,"url":"http://en.wikipedia.org/wiki/Questrecques","text":"Questrecques is a French commune in the region Nord-Pas-de-Calais, in the Pas-de-Calais department in north France.\nQuestrecques is 7 miles (11\u00A0km) southeast of Boulogne-sur-Mer. It is on the riverbanks of the River Liane.\nThe number of people living in Questrecques goes up most years.\nIn France, there is a big survey called a census. In the census, the government finds out how many people live in a place.\nThere is a church in Questrecques. It is called The Church of St. Martin. It is a 15th century church.","categories":[],"infobox_types":[],"annotations":[{"uri":"Communes_of_France","surface_form":"French commune","offset":18},{"uri":"Regions_of_France","surface_form":"region","offset":40},{"uri":"Nord-Pas-de-Calais","surface_form":"Nord-Pas-de-Calais","offset":47},{"uri":"Pas-de-Calais","surface_form":"Pas-de-Calais","offset":74},{"uri":"Departments_of_France","surface_form":"department","offset":88},{"uri":"France","surface_form":"France","offset":108},{"uri":"Mile","surface_form":"mile","offset":134},{"uri":"Southeast","surface_form":"southeast","offset":148},{"uri":"Boulogne-sur-Mer","surface_form":"Boulogne-sur-Mer","offset":161},{"uri":"River","surface_form":"river","offset":192},{"uri":"Census","surface_form":"census","offset":329},{"uri":"Government","surface_form":"government","offset":356},{"uri":"15th_century","surface_form":"15th century","offset":492}]}