{"id":192771,"url":"http://en.wikipedia.org/wiki/Baccarat%2C_Meurthe-et-Moselle","text":"Baccarat is a town in the Meurthe-et-Moselle area in northeastern France.\nCrystal.\nIn 1764, King Louis the fifteenth allowed to the Bishop of Metz to start a glass factory at Baccarat. The Baccarat crystalworks are famous for their glass and crystal artwork, and the Mus\u00E9e du Cristal, owned by the company, is Lorraine's biggest private museum.\nSights.\nThe Church of Saint R\u00E9my is well known for its artistic glass windows.","categories":[],"infobox_types":[],"annotations":[{"uri":"Communes_of_France","surface_form":"town","offset":14},{"uri":"Meurthe-et-Moselle","surface_form":"Meurthe-et-Moselle","offset":26},{"uri":"Departments_of_France","surface_form":"area","offset":45},{"uri":"France","surface_form":"France","offset":66},{"uri":"Louis_XV_of_France","surface_form":"Louis the fifteenth","offset":97},{"uri":"Bishop_of_Metz","surface_form":"Bishop of Metz","offset":132},{"uri":"Baccarat_(company)","surface_form":"Baccarat crystalworks","offset":189},{"uri":"Crystal","surface_form":"crystal","offset":242}]}