{"id":223243,"url":"http://en.wikipedia.org/wiki/Freedom_of_information","text":"e=\"preserve\">Freedom of information is the right to freedom of expression on the Internet and other information technology. Freedom of information is the ability to access the Web without censorship or restrictions.\nFreedom of information is a human right recognised in international law. Freedom of speech includes not only the text and pictures but also the means of expression. Freedom of information may also refer to the right to privacy in the context of the Internet and information technology. The \"right to privacy\" is a human right and freedom of information is an extension of this right.","categories":[],"infobox_types":[],"annotations":[{"uri":"Freedom_of_expression","surface_form":"freedom of expression","offset":52},{"uri":"Internet","surface_form":"Internet","offset":81},{"uri":"Information_technology","surface_form":"information technology","offset":100},{"uri":"World_Wide_Web","surface_form":"Web","offset":176},{"uri":"Censorship","surface_form":"censorship","offset":188},{"uri":"Human_right","surface_form":"human right","offset":244},{"uri":"International_law","surface_form":"international law","offset":270},{"uri":"Freedom_of_speech","surface_form":"Freedom of speech","offset":289},{"uri":"Right_to_privacy","surface_form":"right to privacy","offset":426},{"uri":"Internet","surface_form":"Internet","offset":465},{"uri":"Information_technology","surface_form":"information technology","offset":478},{"uri":"Human_right","surface_form":"human right","offset":530}]}