{"id":23065,"url":"http://en.wikipedia.org/wiki/UEFA_Champions_League","text":"The UEFA Champions League, or simply known as the UCL is a football competition organized by UEFA, between some of the top club teams in Europe. The teams are selected because of good performances in their league matches. The teams used to have to win their countries' championship, but more than one team can play in the competition depending on how good their league is. For example: the Spanish League can get 4 Spanish clubs in the competition compared to the Kazakhstan League which can only get one team in the competition.\nReal Madrid won the Champions League the first five times it was held, still a record. They have also won the Champions League/European Cup 13 times, which is also a record.\nA total of 22 clubs from 10 European countries won the Champions League. 12 clubs won it more than once: Real Madrid, Milan, Bayern, Liverpool, Barcelona, Ajax, Manchester United, Inter Milan, Juventus, Benfica, Porto and Nottingham Forest. The current champions are Bayern Munich after defeating Paris Saint-Germain in the final on 23rd August 2020 by 1-0.","categories":[],"infobox_types":["football tournament"],"annotations":[{"uri":"Football_(soccer)","surface_form":"football","offset":59},{"uri":"UEFA","surface_form":"UEFA","offset":93},{"uri":"Europe","surface_form":"Europe","offset":137},{"uri":"Real_Madrid","surface_form":"Real Madrid","offset":809},{"uri":"Milan","surface_form":"Milan","offset":822},{"uri":"Bayern","surface_form":"Bayern","offset":829},{"uri":"Liverpool","surface_form":"Liverpool","offset":837},{"uri":"Barcelona","surface_form":"Barcelona","offset":848},{"uri":"Ajax","surface_form":"Ajax","offset":859},{"uri":"Manchester_United","surface_form":"Manchester United","offset":865},{"uri":"Inter_Milan","surface_form":"Inter Milan","offset":884},{"uri":"Juventus","surface_form":"Juventus","offset":897},{"uri":"Benfica","surface_form":"Benfica","offset":907},{"uri":"Porto","surface_form":"Porto","offset":916},{"uri":"Nottingham_Forest","surface_form":"Nottingham Forest","offset":926}]}