{"id":288007,"url":"http://en.wikipedia.org/wiki/Long_pepper","text":"Long pepper (\"Piper longum\"), also known as the Indonesian long pepper, is a flowering vine in the family \"Piperaceae\", known for its fruit, which is usually dried and used as a spice.\nUses.\nToday, long pepper is a very rare ingredient in European cuisines, but it can still be found in Pakistani vegetable pickles, some North African spice mixtures, and in Indonesian and Malaysian cooking.","categories":[],"infobox_types":[],"annotations":[{"uri":"Flowering_plant","surface_form":"flowering","offset":77},{"uri":"Vine","surface_form":"vine","offset":87},{"uri":"Piperaceae","surface_form":"Piperaceae","offset":107},{"uri":"Fruit","surface_form":"fruit","offset":134},{"uri":"Dry","surface_form":"dried","offset":158},{"uri":"Spice","surface_form":"spice","offset":178},{"uri":"Europe","surface_form":"European","offset":239},{"uri":"Pakistan","surface_form":"Pakistani","offset":287},{"uri":"Vegetable","surface_form":"vegetable","offset":297},{"uri":"North_Africa","surface_form":"North Africa","offset":321},{"uri":"Spice","surface_form":"spice","offset":335},{"uri":"Indonesia","surface_form":"Indonesia","offset":358},{"uri":"Malaysia","surface_form":"Malaysia","offset":373}]}