{"id":311330,"url":"http://en.wikipedia.org/wiki/3LW","text":"3LW (Three Little Women) were an American girl group. The group consist of Naturi Cora Maria Naughton, born May 20, 1984, Adrienne Eliza Bailon, born October 24, 1983, Kiely Alexis Williams, born July 9, 1986. The band formed in 1999 in Newark, New Jersey.\nIn August 2002, Naturi Naughton announced that she had been forced out of 3LW. Before the year's end, the ladies held various auditions in Atlanta, Los Angeles and New York in search of a third member. Jessica Benson made the cut and joined 3LW in December. The group disbanded in 2007.","categories":[],"infobox_types":[],"annotations":[{"uri":"United_States","surface_form":"American","offset":33},{"uri":"Girl_group","surface_form":"girl group","offset":42},{"uri":"Newark%2C_New_Jersey","surface_form":"Newark, New Jersey","offset":237},{"uri":"Atlanta","surface_form":"Atlanta","offset":396},{"uri":"Los_Angeles","surface_form":"Los Angeles","offset":405},{"uri":"New_York","surface_form":"New York","offset":421}]}