{"id":314979,"url":"http://en.wikipedia.org/wiki/Herman_Wouk","text":"Herman Wouk (May 27, 1915 \u2013 May 17, 2019) was a Pulitzer Prize winning American writer. He was from New York City, New York. Wouk had written many books including \"The Caine Mutiny\". He won Pulitzer Prize award in 1952.\nWouk was Orthodox Jewish and was known for his defence of religion, tradition, American patriotism and the Military.\nWouk died in his sleep at his home in Palm Springs, California on May 17, 2019, 10 days before his 104th birthday.","categories":[],"infobox_types":["writer &lt;!-- for more information see [[:Template:Infobox writer/doc]] --&gt;"],"annotations":[{"uri":"Pulitzer_Prize","surface_form":"Pulitzer Prize","offset":48},{"uri":"United_States","surface_form":"American","offset":71},{"uri":"Writer","surface_form":"writer","offset":80},{"uri":"New_York_City","surface_form":"New York City","offset":100},{"uri":"New_York","surface_form":"New York","offset":115},{"uri":"Book","surface_form":"book","offset":147},{"uri":"The_Caine_Mutiny","surface_form":"The Caine Mutiny","offset":164},{"uri":"Orthodox","surface_form":"Orthodox","offset":229},{"uri":"Jewish","surface_form":"Jewish","offset":238},{"uri":"Religion","surface_form":"religion","offset":278},{"uri":"Tradition","surface_form":"tradition","offset":288},{"uri":"American","surface_form":"American","offset":299},{"uri":"Patriotism","surface_form":"patriotism","offset":308},{"uri":"Military.","surface_form":"Military.","offset":327},{"uri":"Palm_Springs%2C_California","surface_form":"Palm Springs, California","offset":375}]}