{"id":319969,"url":"http://en.wikipedia.org/wiki/Hans_Motz","text":"e=\"preserve\">Hans Motz (1 October 1909 \u2013 6 August 1987) was an Austrian physicist. He worked at Stanford University on undulators. His work led to the development of the free-electron laser.\nHe was born in Vienna, and died in Oxford, England.\nHans Motz was a Full Professor in the Department of Engineering at Oxford University and a Fellow of St Catherine's College, Oxford.\nHe wrote books, including \"The Physics of Fusion\", and a book on microwave theory. When he died, he left money to Oxford to establish a Motz Prize in Electrical Engineering to honor top students.","categories":[],"infobox_types":[],"annotations":[{"uri":"Austria","surface_form":"Austria","offset":63},{"uri":"Physicist","surface_form":"physicist","offset":72},{"uri":"Work","surface_form":"work","offset":86},{"uri":"Stanford_University","surface_form":"Stanford University","offset":96},{"uri":"Undulator","surface_form":"undulator","offset":119},{"uri":"Development","surface_form":"development","offset":151},{"uri":"Free-electron_laser","surface_form":"free-electron laser","offset":170},{"uri":"Vienna","surface_form":"Vienna","offset":206},{"uri":"Oxford","surface_form":"Oxford","offset":226},{"uri":"England","surface_form":"England","offset":234},{"uri":"Professor","surface_form":"Professor","offset":264},{"uri":"Academic_department","surface_form":"Department","offset":281},{"uri":"Engineering","surface_form":"Engineering","offset":295},{"uri":"Oxford_University","surface_form":"Oxford University","offset":310},{"uri":"St_Catherine%27s_College%2C_Oxford","surface_form":"St Catherine's College, Oxford","offset":344},{"uri":"Book","surface_form":"book","offset":385}]}