{"id":345570,"url":"http://en.wikipedia.org/wiki/Cumilla","text":"Comilla is a metropolitan city in south-eastern Bangladesh. It is the third largest city in Bangladesh. It is along the Dhaka-Chittagong Highway. It is the center of the Comilla District and part of the Chittagong Division. It is one of the oldest cities in Bangladesh.\nThe Eastern Wing of Bangladesh Highway Police is in Comilla. The Gomti River and Little Feni River pass through the city. The Tropic of Cancer crosses Comilla city on the south side.\nThe Comilla Victorians are a professional cricket team. They play in the Bangladesh Premier League.","categories":[],"infobox_types":[],"annotations":[{"uri":"Bangladesh","surface_form":"Bangladesh","offset":48},{"uri":"Dhaka-Chittagong_Highway","surface_form":"Dhaka-Chittagong Highway","offset":120},{"uri":"Comilla_District","surface_form":"Comilla District","offset":170},{"uri":"Chittagong_Division","surface_form":"Chittagong Division","offset":203},{"uri":"Gomti_River","surface_form":"Gomti River","offset":335},{"uri":"Tropic_of_Cancer","surface_form":"Tropic of Cancer","offset":396},{"uri":"Comilla_Victorians","surface_form":"Comilla Victorians","offset":457},{"uri":"Cricket","surface_form":"cricket","offset":495},{"uri":"Bangladesh_Premier_League","surface_form":"Bangladesh Premier League","offset":526}]}