{"id":357022,"url":"http://en.wikipedia.org/wiki/Colegio_de_la_Preciosa_Sangre","text":"Colegio de la Preciosa Sangre is a Chilean private state-subsidized primary and secondary school in the coastal town of Pichilemu. It is also known by the name Preciosa Sangre.\nThe school ranks first in Cardenal Caro Province, based on the scores from the \"Prueba de Selecci\u00F3n Universitaria\" (PSU) test, taken each December. The school has been qualified as the \"best school in Pichilemu\", and \"a regional icon\" by Region of O'Higgins newspaper \"El Rancag\u00FCino\".","categories":[],"infobox_types":[],"annotations":[{"uri":"Chile","surface_form":"Chile","offset":35},{"uri":"Pichilemu","surface_form":"Pichilemu","offset":120},{"uri":"Region_of_O%27Higgins","surface_form":"Region of O'Higgins","offset":415},{"uri":"El_Rancag%C3%BCino","surface_form":"El Rancag\u00FCino","offset":446}]}