{"id":359099,"url":"http://en.wikipedia.org/wiki/August_Ludwig_von_Schl%C3%B6zer","text":"August Ludwig von Schl\u00F6zer (5 July 1735 \u2014 9 September 1809) was a German historian. He made many important contributions to the study of the Universal History, and particularly, the History of Russia.\nIn 1804, Schl\u00F6zer was ennobled and elected privy councilor by the Russian Tsar Alexander I of Russia\nHis outlook about the universal history influenced historians as Nikolai Karamzin.","categories":[],"infobox_types":[],"annotations":[{"uri":"Universal_History","surface_form":"Universal History","offset":141},{"uri":"Russia","surface_form":"History of Russia","offset":182},{"uri":"1804","surface_form":"1804","offset":204},{"uri":"Tsar","surface_form":"Tsar","offset":275},{"uri":"Alexander_I_of_Russia","surface_form":"Alexander I of Russia","offset":280},{"uri":"Nikolai_Karamzin","surface_form":"Nikolai Karamzin","offset":367}]}