{"id":447205,"url":"http://en.wikipedia.org/wiki/Deliver_Us_from_Evil","text":"\"Deliver Us from Evil\" is a 2014 crime and horror movie. It is about a New York City police officer who gets pulled into a case that is demon-related. Eric Bana plays the officer, Ralph Sarchie. Olivia Munn plays his wife.\nThe movie is based on a 2001 book called \"Beware the Night\". Screen Gems distributes the movie.\nThe movie was released on July 2, 2014.","categories":[],"infobox_types":[],"annotations":[{"uri":"Horror_movie","surface_form":"horror movie","offset":43},{"uri":"New_York_City","surface_form":"New York City","offset":71},{"uri":"Demon","surface_form":"demon","offset":136},{"uri":"Eric_Bana","surface_form":"Eric Bana","offset":151},{"uri":"Olivia_Munn","surface_form":"Olivia Munn","offset":195}]}