{"id":482180,"url":"http://en.wikipedia.org/wiki/IFK_V%C3%A4xj%C3%B6","text":"IFK V\u00E4xj\u00F6 is a sports club in the town of V\u00E4xj\u00F6 in Sweden. It was established on 2 June 1919. The club runs track and field athletics and disabled sports. It earlier also ran bandy and soccer. The men's bandy team played in the Swedish top division in 1941. The women's soccer activity was transferred to \u00D6sters IF in 1983. That led to the establishments of \u00D6sters IF dam.\nCarolina Kl\u00FCft has competed for the club.","categories":[],"infobox_types":[],"annotations":[{"uri":"Sports_club","surface_form":"sports club","offset":15},{"uri":"V%C3%A4xj%C3%B6","surface_form":"V\u00E4xj\u00F6","offset":42},{"uri":"Sweden","surface_form":"Sweden","offset":51},{"uri":"Track_and_field_athletics","surface_form":"track and field athletics","offset":108},{"uri":"Disabled_sports","surface_form":"disabled sports","offset":138},{"uri":"Bandy","surface_form":"bandy","offset":175},{"uri":"Association_football","surface_form":"soccer","offset":185},{"uri":"Women%27s_association_football","surface_form":"women's soccer","offset":262},{"uri":"%C3%96sters_IF","surface_form":"\u00D6sters IF","offset":305},{"uri":"%C3%96sters_IF_dam","surface_form":"\u00D6sters IF dam","offset":358},{"uri":"Carolina_Kl%C3%BCft","surface_form":"Carolina Kl\u00FCft","offset":373}]}