{"id":539496,"url":"http://en.wikipedia.org/wiki/Tommy_Kono","text":"Tamio \"Tommy\" Kono (June 27, 1930 \u2013 April 24, 2016) was an American weightlifter in the 1950s and 1960s.\nKono was the only Olympic weightlifter in history to have set world records in four different weight classes: lightweight (149\u00A0pounds or 67.5\u00A0kilograms), middleweight (165\u00A0lb or 75\u00A0kg), light-heavyweight (182\u00A0lb or 82.5\u00A0kg), and middle-heavyweight (198\u00A0lb or 90\u00A0kg).\nIn 1993 Kono was elected to the International Weightlifting Federation Hall of Fame. Kono was also an inductee to the Association of Oldetime Barbell and Strongmen (A.O.B.S.) Hall of Fame.\nKono died on April 24, 2016 in Honolulu, Hawaii from complications of liver disease, aged 85.","categories":[],"infobox_types":[],"annotations":[{"uri":"Americans","surface_form":"American","offset":59},{"uri":"Olympic_weightlifting","surface_form":"weightlifter","offset":68},{"uri":"International_Weightlifting_Federation","surface_form":"International Weightlifting Federation","offset":404},{"uri":"Hall_of_fame","surface_form":"Hall of Fame","offset":443},{"uri":"Honolulu","surface_form":"Honolulu","offset":592},{"uri":"Hawaii","surface_form":"Hawaii","offset":602},{"uri":"Liver_disease","surface_form":"liver disease","offset":631}]}