{"id":548186,"url":"http://en.wikipedia.org/wiki/Time_in_North_Korea","text":"=\"preserve\">Time in North Korea is given Korea Standard Time (KST) which is 8.5 hours ahead of Coordinated Universal Time (UTC). If it is 16:00 UTC, it is 01:00 the next day in North Korea. It has never observed summer time.\nNorth Korea was originally 8:30 hours ahead of UTC () from 2015 to 2018, 30 minutes behind neighboring South Korea and Japan, as announced in August 2015, but reverted to UTC+09:00 now on the same time as Seoul and Tokyo beginning at 23:30 on 4 May 2018.","categories":[],"infobox_types":[],"annotations":[{"uri":"North_Korea","surface_form":"North Korea","offset":20},{"uri":"Coordinated_Universal_Time","surface_form":"Coordinated Universal Time","offset":95},{"uri":"Daylight_saving_time","surface_form":"summer time","offset":212},{"uri":"South_Korea","surface_form":"South Korea","offset":328},{"uri":"Japan","surface_form":"Japan","offset":344}]}