{"id":565397,"url":"http://en.wikipedia.org/wiki/Glyfada","text":"Glyfada is a district in southern Athens and a famous coastal resort.\nThe area developed as a tourist destination through the 1970s and 1980s and has a large number of hotels, shops, restaurants and clubs. It is situated close to the old international airport.","categories":[],"infobox_types":[],"annotations":[{"uri":"Athens","surface_form":"Athens","offset":34},{"uri":"Tourism","surface_form":"tourist destination","offset":94}]}