{"id":570461,"url":"http://en.wikipedia.org/wiki/Gordon_Aikman","text":"e=\"preserve\">Gordon Lewis Aikman (2 April 1985 \u2013 3 February 2017) was a British political researcher and campaigner. He was a Director of Research for the Better Together campaign that took place during the Scottish independence referendum in 2014. During that campaign, he was diagnosed with motor neurone disease. He later went on to campaign to raise awareness of the disease.\nAikman was born in Kirkcaldy, Fife. He was married to Joe Pike.\nAikman died from motor neurone disease on 3 February 2017 at the age of 31.","categories":[],"infobox_types":[],"annotations":[{"uri":"British_people","surface_form":"British","offset":72},{"uri":"Political","surface_form":"political","offset":80},{"uri":"Researcher","surface_form":"researcher","offset":90},{"uri":"Campaign","surface_form":"campaign","offset":105},{"uri":"Better_Together_(campaign)","surface_form":"Better Together","offset":155},{"uri":"Scottish_independence_referendum","surface_form":"Scottish independence referendum","offset":207},{"uri":"Motor_neurone_disease","surface_form":"motor neurone disease","offset":293},{"uri":"Kirkcaldy","surface_form":"Kirkcaldy","offset":399},{"uri":"Fife","surface_form":"Fife","offset":410}]}