{"id":655169,"url":"http://en.wikipedia.org/wiki/Margit_Sandemo","text":"Margit Sandemo (, 23 April 1924 \u2013 1 September 2018) was a Norwegian-Swedish author. She had been the best-selling author in the Nordic Countries since the 1980s, when her novel series of 47 books, \"The Legend of the Ice People\", was published. She also wrote many other book series such as \"H\u00E4xm\u00E4staren\" and \"Legenden om Ljusets rike\".\nSandemo was born on 23 April 1924 in Lena, Norway and died on 1 September 2018 in Scania, Sweden at the age of 94.","categories":[],"infobox_types":[],"annotations":[{"uri":"Norwegians","surface_form":"Norwegian","offset":58},{"uri":"Swedish_people","surface_form":"Swedish","offset":68},{"uri":"Author","surface_form":"author","offset":76},{"uri":"Nordic_countries","surface_form":"Nordic Countries","offset":128},{"uri":"The_Legend_of_the_Ice_People","surface_form":"The Legend of the Ice People","offset":198},{"uri":"H%C3%A4xm%C3%A4staren","surface_form":"H\u00E4xm\u00E4staren","offset":291},{"uri":"Legenden_om_Ljusets_rike","surface_form":"Legenden om Ljusets rike","offset":309},{"uri":"%C3%98stre_Toten","surface_form":"Lena","offset":373},{"uri":"Norway","surface_form":"Norway","offset":379},{"uri":"Sk%C3%A5ne","surface_form":"Scania","offset":418},{"uri":"Sweden","surface_form":"Sweden","offset":426}]}