{"id":744254,"url":"http://en.wikipedia.org/wiki/Martin_Davorin-Jagodi%C4%87","text":"e=\"preserve\">Martin Davorin Jagodi\u0107 (16 December 1935 \u2013 8 March 2020) was a Croatian contemporary music composer and educator. He was born in Pag, Croatia. Jagodi\u0107 composed music for several experimental movies, starting with \"Environment\" in 1969.\nHis career as an educator started in 1969 as assistant and then lecturer at the music department of Universit\u00E9 de Vincennes Paris 8, later also teaching stage design and scenography at Ecole Nationale Sup\u00E9rieure des Arts D\u00E9coratifs from 1974 to 1988.\nIn the 1990s, he taught musicology at Universit\u00E9 de Saint-Denis, after the \"Universit\u00E9 de Vincennes Paris 8\" had relocated there in 1980. He died on 8 March 2020 in Auxerre, France at the age of 84.","categories":[],"infobox_types":[],"annotations":[{"uri":"Pag","surface_form":"Pag","offset":142},{"uri":"Croatia","surface_form":"Croatia","offset":147},{"uri":"Universit%C3%A9_Paris_8","surface_form":"Universit\u00E9 de Vincennes Paris 8","offset":349},{"uri":"Auxerre","surface_form":"Auxerre","offset":665},{"uri":"France","surface_form":"France","offset":674}]}