{"id":760409,"url":"http://en.wikipedia.org/wiki/United_States_Senate_Energy_Subcommittee_on_Energy","text":"e=\"preserve\">The United States Senate Energy and Natural Resources Subcommittee on Energy is one of four subcommittees of the U.S. Senate Energy and Natural Resources Committee.\nSome of the things they deal with include nuclear, coal and synthetic fuels research and development; nuclear and non-nuclear energy projects and oil/gas pipelines.","categories":[],"infobox_types":[],"annotations":[{"uri":"United_States","surface_form":"United States","offset":17},{"uri":"United_States_Senate_Committee_on_Energy_and_Natural_Resources","surface_form":"U.S. Senate Energy and Natural Resources Committee","offset":126},{"uri":"Nuclear_power","surface_form":"nuclear","offset":220},{"uri":"Coal","surface_form":"coal","offset":229},{"uri":"Synthetic_fuel","surface_form":"synthetic fuel","offset":238},{"uri":"Research_and_development","surface_form":"research and development","offset":254}]}