{"id":764475,"url":"http://en.wikipedia.org/wiki/Abdelmalek_Droukdel","text":"e=\"preserve\">Abdelmalek Droukdel (; 20 April 1970 &ndash 3 June 2020) also known by his nom de guerre as Abu Musab Abdel Wadoud (), was the emir leader of the Algerian Islamic militant group Al-Qaeda in the Islamic Maghreb (AQIM). He was born in Meftah, Algeria.\nHis death was announced on 5 June 2020 that Droukdel, and members of his inner circle, had been killed by its forces in an operation in the north of Mali two days earlier.","categories":[],"infobox_types":[],"annotations":[{"uri":"Nom_de_guerre","surface_form":"nom de guerre","offset":88},{"uri":"Islamic_militant","surface_form":"Islamic militant","offset":168},{"uri":"Al-Qaeda_in_the_Islamic_Maghreb","surface_form":"Al-Qaeda in the Islamic Maghreb","offset":191},{"uri":"Meftah_(town)","surface_form":"Meftah","offset":246},{"uri":"Algeria","surface_form":"Algeria","offset":254}]}