{"id":768005,"url":"http://en.wikipedia.org/wiki/President_of_the_Senate_of_Chile","text":"e=\"preserve\">The President of the Senate of Chile is the highest authority of the Senate of Chile. The position comes after the Ministers of State in the line of succession of the President of Chile.\nThe President of the Senate receives no special treatment in the sessions of Senate. However, in the official communications the President holds the title of \"Excelencia\" (\"Excellency\"). He or she is elected, from the body of current Senators.","categories":[],"infobox_types":[],"annotations":[{"uri":"Senate_of_Chile","surface_form":"Senate of Chile","offset":82},{"uri":"Cabinet_(government)","surface_form":"Ministers of State","offset":128},{"uri":"Line_of_succession","surface_form":"line of succession","offset":154},{"uri":"President_of_Chile","surface_form":"President of Chile","offset":180}]}