{"id":800691,"url":"http://en.wikipedia.org/wiki/Bruce_Hurley","text":"=\"preserve\">Bruce Hurley (February 16, 1934 \u2013 November 4, 2020) was an American politician. He was in the Tennessee House of Representatives as a Republican from the 9th District from 1971 to 1989. Hurley was born in Hancock County, Tennessee.\nHurley died on November 4, 2020 in Kingsport, Tennessee at the age of 86.","categories":[],"infobox_types":[],"annotations":[{"uri":"Tennessee_House_of_Representatives","surface_form":"Tennessee House of Representatives","offset":106},{"uri":"Republican_Party_(United_States)","surface_form":"Republican","offset":146},{"uri":"Hancock_County%2C_Tennessee","surface_form":"Hancock County, Tennessee","offset":217},{"uri":"Kingsport%2C_Tennessee","surface_form":"Kingsport, Tennessee","offset":279}]}