{"id":801088,"url":"http://en.wikipedia.org/wiki/Shk%C3%ABlqim_Troplini","text":"e=\"preserve\">Shk\u00EBlqim Troplini (1 October 1966 \u2013 7 November 2020) was an Albanian wrestler. He competed in the 1996 Summer Olympics.\nOn 7 November 2020, Troplini died of COVID-19 at the age of 54.","categories":[],"infobox_types":[],"annotations":[{"uri":"Albania","surface_form":"Albania","offset":73},{"uri":"Amateur_wrestling","surface_form":"wrestler","offset":82},{"uri":"1996_Summer_Olympics","surface_form":"1996 Summer Olympics","offset":111},{"uri":"COVID-19","surface_form":"COVID-19","offset":170}]}