{"id":814222,"url":"http://en.wikipedia.org/wiki/Vero_Boquete","text":"=\"preserve\">Ver\u00F3nica Boquete (Santiago de Compostela, Galicia, April 9, 1987) is a Spanish footballer who plays as a midfielder for the Associazione Calcio Milan of Serie A in Italy. She was international with the Spanish team, of which she became captain.\nSince February 2015 she has been a UEFA ambassador for the development of women's football, and since 2017 she has been part of the CommonGoal community of footballers, an initiative led by Juan Mata, also from Spain, who fights for the social reintegration of children in through the funds raised with 1% of the salary of the community footballers.","categories":[],"infobox_types":[],"annotations":[{"uri":"A.C._Milan","surface_form":"Associazione Calcio Milan","offset":136},{"uri":"Serie_A","surface_form":"Serie A","offset":165},{"uri":"Italy","surface_form":"Italy","offset":176}]}