{"id":84709,"url":"http://en.wikipedia.org/wiki/County_Down","text":"County Down'\", (\"Contae an D\u00FAin\" in Irish - meaning \"the Fort\") is one of six counties that form Northern Ireland, and one of the nine counties of the ancient province of Ulster\nThe county forms an area of 2,448 km\u00B2 (945 square miles). The estimated population in 1992 was 416,600, a more recent approximation puts it at about 516,000. The county town is Downpatrick, and the largest town is Bangor.","categories":[],"infobox_types":[],"annotations":[{"uri":"Irish_language","surface_form":"Irish","offset":36},{"uri":"Counties_of_Ireland","surface_form":"counties","offset":78},{"uri":"Northern_Ireland","surface_form":"Northern Ireland","offset":97},{"uri":"Counties_of_Ireland","surface_form":"counties","offset":135},{"uri":"Ulster","surface_form":"Ulster","offset":171},{"uri":"Km","surface_form":"km","offset":212},{"uri":"Square_mile","surface_form":"square mile","offset":221},{"uri":"Population","surface_form":"population","offset":250},{"uri":"1992","surface_form":"1992","offset":264},{"uri":"Bangor%2C_County_Down","surface_form":"Bangor","offset":392}]}